yastrider/__init__.py
yastrider/_validation.py
yastrider/char_removal.py
yastrider/constants.py
yastrider/diacritics_processing.py
yastrider/formatting.py
yastrider/normalization.py
yastrider/py.typed
yastrider/redaction.py
yastrider/utils.py
yastrider/version.py
yastrider-0.2.1.dist-info/licenses/LICENSE
yastrider-0.2.1.dist-info/METADATA
yastrider-0.2.1.dist-info/WHEEL
yastrider-0.2.1.dist-info/top_level.txt
yastrider-0.2.1.dist-info/RECORD
