Metadata-Version: 2.4
Name: yastrider
Version: 0.2.1
Summary: Yet another string tidier: A small, predictable, dependency-free toolkit for defensive string cleansing and tidying.
Author: Martín Barranca Rábago
License: MIT License
Project-URL: Homepage, https://github.com/barrank/yastrider
Project-URL: Source, https://github.com/barrank/yastrider
Project-URL: Issues, https://github.com/barrank/yastrider/issues
Keywords: text,unicode,normalization,redaction,ascii,formatting
Classifier: Development Status :: 3 - Alpha
Classifier: Intended Audience :: Developers
Classifier: License :: OSI Approved :: MIT License
Classifier: Operating System :: OS Independent
Classifier: Programming Language :: Python :: 3 :: Only
Classifier: Programming Language :: Python :: 3.10
Classifier: Topic :: Text Processing
Classifier: Topic :: Software Development :: Libraries :: Python Modules
Requires-Python: >=3.10
License-File: LICENSE
Provides-Extra: dev
Requires-Dist: pytest; extra == "dev"
Dynamic: license-file
